{
  "_id": "product-sql01_vot-endpoint",
  "type": "pipe",
  "source": {
    "type": "dataset",
    "dataset": "visma-olavstoppen-product"
  },
  "sink": {
    "type": "sql",
    "system": "sql01_vot",
    "create_table_if_missing": true,
    "primary_key": "ProductNo",
    "schema": "dbo",
    "schema_definition": [{
      "type": "datetime",
      "name": "Created",
      "allow_null": true,
      "max_value": "~t2120-06-26T10:25:59Z",
      "min_value": "~t2011-03-11T16:47:34Z",
      "source_property": "Created"
    }, {
      "type": "integer",
      "name": "CreatedBy",
      "allow_null": true,
      "max_value": 10000,
      "min_value": 1,
      "source_property": "CreatedBy"
    }, {
      "type": "integer",
      "name": "DepNo",
      "allow_null": true,
      "max_value": 10000,
      "min_value": 0,
      "source_property": "DepNo"
    }, {
      "type": "integer",
      "name": "InActiveYesNo",
      "allow_null": true,
      "max_value": 1,
      "min_value": 0,
      "source_property": "InActiveYesNo"
    }, {
      "type": "datetime",
      "name": "LastUpdate",
      "allow_null": true,
      "max_value": "~t2120-06-29T16:30:17Z",
      "min_value": "~t2011-04-07T10:16:42Z",
      "source_property": "LastUpdate"
    }, {
      "type": "integer",
      "name": "LastUpdatedBy",
      "allow_null": true,
      "max_value": 10000,
      "min_value": 2,
      "source_property": "LastUpdatedBy"
    }, {
      "type": "integer",
      "name": "MDM_Deleted",
      "allow_null": true,
      "max_value": 1,
      "min_value": 0,
      "source_property": "MDM_Deleted"
    }, {
      "type": "string",
      "name": "MDM_ExternalId",
      "allow_null": true,
      "max_size": 36,
      "min_size": 36,
      "source_property": "MDM_ExternalId"
    }, {
      "type": "string",
      "name": "MDM_PublicId",
      "allow_null": true,
      "max_size": 36,
      "min_size": 36,
      "source_property": "MDM_PublicId"
    }, {
      "type": "integer",
      "name": "MDM_SyncVersion",
      "allow_null": true,
      "max_value": 100,
      "min_value": 1,
      "source_property": "MDM_SyncVersion"
    }, {
      "type": "integer",
      "name": "MDM_Version",
      "allow_null": true,
      "max_value": 100,
      "min_value": 1,
      "source_property": "MDM_Version"
    }, {
      "type": "string",
      "name": "Name",
      "allow_null": true,
      "max_size": 100,
      "min_size": 1,
      "source_property": "Name"
    }, {
      "type": "integer",
      "name": "ProductNo",
      "max_value": 100000,
      "min_value": 1,
      "primary_key": true,
      "source_property": "ProductNo"
    }, {
      "type": "integer",
      "name": "RespEmployeeNo",
      "allow_null": true,
      "max_value": 10000,
      "min_value": 0,
      "source_property": "RespEmployeeNo"
    }, {
      "type": "datetime",
      "name": "StartTime",
      "allow_null": true,
      "max_value": "~t2120-01-01T00:00:00Z",
      "min_value": "~t1970-01-01T00:00:00Z",
      "source_property": "StartTime"
    }, {
      "type": "datetime",
      "name": "StopTime",
      "allow_null": true,
      "max_value": "~t2099-12-31T00:00:00Z",
      "min_value": "~t1970-01-01T00:00:00Z",
      "source_property": "StopTime"
    }, {
      "type": "integer",
      "name": "TransferNewYearYesNo",
      "allow_null": true,
      "max_value": 1,
      "min_value": 0,
      "source_property": "TransferNewYearYesNo"
    }, {
      "type": "datetime",
      "name": "LastUploadDataStorage",
      "allow_null": true,
      "max_value": "~t2100-01-01T00:00:00Z",
      "min_value": "~t1970-01-01T00:00:00Z",
      "source_property": "LastUploadDataStorage"
    }, {
      "type": "binary",
      "name": "UtilityBits",
      "allow_null": true,
      "max_size": 16,
      "min_size": 2,
      "source_property": "UtilityBits"
    }],
    "table": "Product"
  },
  "pump": {
    "cron_expression": "$ENV(vot_cron_fast)",
    "mode": "$ENV(pump-mode)"
  }
}
